salmon/__init__.py
salmon/_version.py
salmon/bounce.py
salmon/commands.py
salmon/confirm.py
salmon/encoding.py
salmon/mail.py
salmon/queue.py
salmon/routing.py
salmon/server.py
salmon/testing.py
salmon/utils.py
salmon/view.py
salmon/_vendor/LICENSE-lmtpd
salmon/_vendor/README.md
salmon/_vendor/asynchat.py
salmon/_vendor/asyncore.py
salmon/_vendor/lmtpd.py
salmon/_vendor/smtpd.py
salmon/data/prototype/README
salmon/data/prototype/muttrc
salmon/data/prototype/app/__init__.py
salmon/data/prototype/app/handlers/__init__.py
salmon/data/prototype/app/handlers/sample.py
salmon/data/prototype/app/model/__init__.py
salmon/data/prototype/config/__init__.py
salmon/data/prototype/config/boot.py
salmon/data/prototype/config/logging.conf
salmon/data/prototype/config/settings.py
salmon/data/prototype/config/test_logging.conf
salmon/data/prototype/config/testing.py
salmon/data/prototype/logs/.gitkeep
salmon/data/prototype/run/.gitkeep
salmon/data/prototype/tests/handlers/__init__.py
salmon/data/prototype/tests/handlers/open_relay_tests.py
salmon/data/prototype/tests/model/__init__.py
salmon/handlers/__init__.py
salmon/handlers/forward.py
salmon/handlers/log.py
salmon/handlers/queue.py
salmon_mail-3.3.0.dist-info/LICENSE
salmon_mail-3.3.0.dist-info/METADATA
salmon_mail-3.3.0.dist-info/WHEEL
salmon_mail-3.3.0.dist-info/entry_points.txt
salmon_mail-3.3.0.dist-info/top_level.txt
salmon_mail-3.3.0.dist-info/RECORD
