Metadata-Version: 2.1
Name: salmon-mail
Version: 3.3.0
Summary: A Python Mail Server
Home-page: https://github.com/moggers87/salmon
Download-URL: http://pypi.python.org/pypi/salmon-mail
Author: Salmon project contributors
Maintainer: Matt Molyneaux
Maintainer-email: moggers87+git@moggers87.co.uk
License: GPLv3
Classifier: License :: OSI Approved :: GNU General Public License v3 (GPLv3)
Classifier: Development Status :: 4 - Beta
Classifier: Programming Language :: Python :: 3
Classifier: Programming Language :: Python :: 3.8
Classifier: Programming Language :: Python :: 3.9
Classifier: Programming Language :: Python :: 3.10
Classifier: Programming Language :: Python :: 3.11
Classifier: Programming Language :: Python :: 3.12
Classifier: Intended Audience :: Developers
Classifier: Topic :: Communications :: Email
Classifier: Topic :: Software Development :: Libraries :: Application Frameworks
Classifier: Programming Language :: Python :: Implementation :: CPython
Classifier: Programming Language :: Python :: Implementation :: PyPy
Requires-Python: >=3.8
License-File: LICENSE
Requires-Dist: chardet
Requires-Dist: click
Requires-Dist: dnspython
Requires-Dist: python-daemon>2.2.0
Provides-Extra: docs
Requires-Dist: sphinx; extra == "docs"
Requires-Dist: sphinx-rtd-theme; extra == "docs"
Requires-Dist: sphinx-click; extra == "docs"
